posest/__init__.py
posest-0.0.1.dist-info/METADATA
posest-0.0.1.dist-info/WHEEL
posest-0.0.1.dist-info/RECORD
