Metadata-Version: 2.1
Name: posest
Version: 0.0.1
Summary: A pacakge for pose estimation.
Author: isaac-fei
Author-email: isaac.omega.fei@gmail.com
Requires-Python: >=3.11,<4.0
Classifier: Programming Language :: Python :: 3
Classifier: Programming Language :: Python :: 3.11
Requires-Dist: torch (>=2.2.1,<3.0.0)
Requires-Dist: torchvision (>=0.17.1,<0.18.0)
